{
    "status": "active",
    "preferred_support_tool": "",
    "profile_api_url": "https://forge-allura.apache.org/rest/u/heiths/profile/",
    "preferred_support_url": "",
    "labels": [],
    "private": false,
    "creation_date": "2014-12-12",
    "socialnetworks": [
        {
            "accounturl": "",
            "socialnetwork": "Twitter"
        },
        {
            "accounturl": "",
            "socialnetwork": "Facebook"
        }
    ],
    "tools": [
        {
            "mount_point": "admin",
            "name": "admin",
            "label": "Admin"
        },
        {
            "mount_point": "wiki",
            "name": "wiki",
            "label": "Wiki"
        },
        {
            "mount_point": "profile",
            "name": "profile",
            "label": "Profile"
        },
        {
            "mount_point": "search",
            "name": "search",
            "label": "Search"
        },
        {
            "mount_point": "activity",
            "name": "activity",
            "label": "Activity"
        }
    ],
    "categories": {
        "developmentstatus": [],
        "environment": [],
        "language": [],
        "license": [],
        "database": [],
        "topic": [],
        "audience": [],
        "translation": [],
        "os": []
    },
    "_id": "548b2d136d19cd59705380a6",
    "name": "u/heiths",
    "url": "https://forge-allura.apache.org/u/heiths/",
    "icon_url": null,
    "video_url": "",
    "screenshots": [],
    "summary": "",
    "short_description": null,
    "moved_to_url": "",
    "shortname": "u/heiths",
    "developers": [
        {
            "url": "https://forge-allura.apache.org/u/heiths/",
            "username": "heiths",
            "name": "Heith Seewald"
        }
    ],
    "external_homepage": ""
}